safewiseagentlib/__init__.py
safewiseagentlib/formats.py
safewiseagentlib/server.py
safewiseagentlib/util.py
safewiseagentlib/device/__init__.py
safewiseagentlib/device/interface.py
safewiseagentlib/device/safewise.py
safewiseagentlib/device/safewise_defs.py
safewiseagentlib/device/ui.py
safewiseagentlib/gpg/__init__.py
safewiseagentlib/gpg/agent.py
safewiseagentlib/gpg/client.py
safewiseagentlib/gpg/decode.py
safewiseagentlib/gpg/encode.py
safewiseagentlib/gpg/keyring.py
safewiseagentlib/gpg/protocol.py
safewiseagentlib/ssh/__init__.py
safewiseagentlib/ssh/client.py
safewiseagentlib/ssh/protocol.py
safewiseagentlib-1.1.0.dist-info/LICENSE
safewiseagentlib-1.1.0.dist-info/METADATA
safewiseagentlib-1.1.0.dist-info/WHEEL
safewiseagentlib-1.1.0.dist-info/top_level.txt
safewiseagentlib-1.1.0.dist-info/RECORD
